LICENSE
MANIFEST.in
README.rst
setup.cfg
setup.py
file_encryptor/__init__.py
file_encryptor/convergence.py
file_encryptor/key_generators.py
file_encryptor/settings.py
file_encryptor.egg-info/PKG-INFO
file_encryptor.egg-info/SOURCES.txt
file_encryptor.egg-info/dependency_links.txt
file_encryptor.egg-info/requires.txt
file_encryptor.egg-info/top_level.txt