Metadata-Version: 1.1
Name: file-encryptor
Version: 0.2.9
Summary: Tool for convergently encrypting files used by MetaDisk.
Home-page: https://github.com/Storj/file-encryptor
Author: Storj Labs
Author-email: hello@storj.io
License: The MIT License (MIT)
